pyDbs/__init__.py
pyDbs/base.py
pyDbs/gpy.py
pyDbs/simpleDB.py
pydbs-0.1.8.dist-info/licenses/LICENSE
pydbs-0.1.8.dist-info/METADATA
pydbs-0.1.8.dist-info/WHEEL
pydbs-0.1.8.dist-info/top_level.txt
pydbs-0.1.8.dist-info/RECORD
