Metadata-Version: 2.4
Name: pyDbs
Version: 0.1.8
Summary: Custom database class (relies on pandas, numpy, scipy)
Home-page: https://github.com/ChampionApe/pyDbs
Author: Rasmus K. Skjødt Berg
Author-email: rasmus.kehlet.berg@econ.ku.dk
Classifier: Programming Language :: Python :: 3
Classifier: License :: OSI Approved :: MIT License
Requires-Python: >=3.11
License-File: LICENSE
Requires-Dist: pandas
Requires-Dist: scipy
Requires-Dist: openpyxl
Dynamic: author
Dynamic: author-email
Dynamic: classifier
Dynamic: description
Dynamic: description-content-type
Dynamic: home-page
Dynamic: license-file
Dynamic: requires-dist
Dynamic: requires-python
Dynamic: summary
